arraylib/.__init__.py.swp
arraylib/.lib.py.swp
arraylib/__init__.py
arraylib/lib.py
arraylib/test/.test_arraylib.py.swp
arraylib/test/test_arraylib.py
arraylib-0.0.0.dist-info/LICENSE
arraylib-0.0.0.dist-info/WHEEL
arraylib-0.0.0.dist-info/METADATA
arraylib-0.0.0.dist-info/RECORD
