Metadata-Version: 2.1
Name: arraylib
Version: 0.0.0
Summary: Library for array computing
Author-email: Nicolas Tessore <n.tessore@ucl.ac.uk>
Requires-Python: >=3.6
Classifier: License :: OSI Approved :: MIT License
Requires-Dist: sphinx ; extra == "docs"
Requires-Dist: furo ; extra == "docs"
Requires-Dist: pytest ; extra == "test"
Requires-Dist: numpy ; extra == "test"
Project-URL: Documentation, https://arraylib.readthedocs.io
Project-URL: Home, https://github.com/ntessore/arraylib
Project-URL: Issues, https://github.com/ntessore/arraylib/issues
Provides-Extra: docs
Provides-Extra: test
